Products.ZopeTree-3.4.0-py3.8-nspkg.pth
Products/ZopeTree/IZopeTree.py
Products/ZopeTree/TreeObjectWrapper.py
Products/ZopeTree/ZopeTree.py
Products/ZopeTree/__init__.py
Products/ZopeTree/tests/test_ZopeTree.py
Products.ZopeTree-3.4.0.dist-info/LICENSE.txt
Products.ZopeTree-3.4.0.dist-info/METADATA
Products.ZopeTree-3.4.0.dist-info/WHEEL
Products.ZopeTree-3.4.0.dist-info/namespace_packages.txt
Products.ZopeTree-3.4.0.dist-info/top_level.txt
Products.ZopeTree-3.4.0.dist-info/RECORD
