Metadata-Version: 2.1
Name: Products.ZopeTree
Version: 3.4.0
Summary: ZopeTree is a light-weight tree implementation.
Home-page: https://github.com/jugmac00/Products.ZopeTree
Author: Philipp von Weitershausen
Author-email: philipp@weitershausen.de
Maintainer: Juergen Gmach
Maintainer-email: juergen.gmach@googlemail.com
Project-URL: Issue Tracker, https://github.com/jugmac00/Products.ZopeTree/issues
Project-URL: Sources, https://github.com/jugmac00/Products.ZopeTree
Classifier: Development Status :: 5 - Production/Stable
Classifier: Environment :: Web Environment
Classifier: Framework :: Zope :: 4
Classifier: Framework :: Zope :: 5
Classifier: Intended Audience :: Developers
Classifier: License :: OSI Approved :: Mozilla Public License 1.1 (MPL 1.1)
Classifier: Programming Language :: Python :: 3
Classifier: Programming Language :: Python :: 3.6
Classifier: Programming Language :: Python :: 3.7
Classifier: Programming Language :: Python :: 3.8
Classifier: Programming Language :: Python :: 3.9
Classifier: Programming Language :: Python :: 3.10
Classifier: Programming Language :: Python :: 3.11
Requires-Python: >3.5
License-File: LICENSE.txt
Requires-Dist: Zope
Requires-Dist: setuptools
Requires-Dist: AccessControl
Requires-Dist: zope.interface
Requires-Dist: zope.testing
Provides-Extra: test
Requires-Dist: pytest (>=6.1.1) ; extra == 'test'
Requires-Dist: pytest-cov ; extra == 'test'
